xgbs
